radheef/__init__.py
radheef/errors.py
radheef/radheef.py
radheef-0.0.3.dist-info/LICENSE
radheef-0.0.3.dist-info/METADATA
radheef-0.0.3.dist-info/WHEEL
radheef-0.0.3.dist-info/top_level.txt
radheef-0.0.3.dist-info/RECORD
