Metadata-Version: 2.1
Name: radheef
Version: 0.0.3
Summary: A python library for getting the meaning/s of a dhivehi word and other related information
Home-page: UNKNOWN
Author: Moots
Author-email: moothymycom@gmail.com
License: MIT License
Keywords: radheef,dhivehi dictionary
Platform: UNKNOWN
Classifier: Development Status :: 3 - Alpha
Classifier: Intended Audience :: Developers
Classifier: Programming Language :: Python :: 3
Classifier: Operating System :: OS Independent
Classifier: License :: OSI Approved :: MIT License
Requires-Dist: requests
Requires-Dist: beautifulsoup4
